nhanes_dl/__init__.py
nhanes_dl/__main__.py
nhanes_dl/download.py
nhanes_dl/types.py
nhanes_dl/utils.py
tests/__init__.py
tests/test_download.py
tests/test_types.py
nhanes_dl-0.0.18.dist-info/LICENSE
nhanes_dl-0.0.18.dist-info/METADATA
nhanes_dl-0.0.18.dist-info/WHEEL
nhanes_dl-0.0.18.dist-info/top_level.txt
nhanes_dl-0.0.18.dist-info/RECORD
