Metadata-Version: 2.1
Name: nhanes-dl
Version: 0.0.18
Summary: A python library for downloading Continous NHANES data into panda dataframes
License: MIT
Project-URL: Bug Tracker, https://github.com/LeviButcher/nhanes-dl/issues
Keywords: nhanes
Classifier: Programming Language :: Python :: 3
Classifier: License :: OSI Approved :: MIT License
Classifier: Operating System :: OS Independent
Requires-Python: >=3.6
License-File: LICENSE
Requires-Dist: pandas >=1.4.2
